jsontables/__init__.py
jsontables/cli.py
jsontables/core.py
jsontables-0.1.0.dist-info/LICENSE
jsontables-0.1.0.dist-info/METADATA
jsontables-0.1.0.dist-info/WHEEL
jsontables-0.1.0.dist-info/entry_points.txt
jsontables-0.1.0.dist-info/top_level.txt
jsontables-0.1.0.dist-info/RECORD
