Metadata-Version: 2.1
Name: jsontables
Version: 0.1.0
Summary: A minimal format for representing tabular data in JSON
Home-page: https://github.com/featrix/json-tables
Author: Mitch Haile
Author-email: mitch.haile@gmail.com
Project-URL: Bug Reports, https://github.com/featrix/json-tables/issues
Project-URL: Source, https://github.com/featrix/json-tables
Project-URL: Documentation, https://github.com/featrix/json-tables
Keywords: json tables dataframe pandas cli pretty-print tabular data
Classifier: Development Status :: 4 - Beta
Classifier: Intended Audience :: Developers
Classifier: Intended Audience :: Science/Research
Classifier: License :: OSI Approved :: MIT License
Classifier: Operating System :: OS Independent
Classifier: Programming Language :: Python :: 3
Classifier: Programming Language :: Python :: 3.7
Classifier: Programming Language :: Python :: 3.8
Classifier: Programming Language :: Python :: 3.9
Classifier: Programming Language :: Python :: 3.10
Classifier: Programming Language :: Python :: 3.11
Classifier: Topic :: Software Development :: Libraries :: Python Modules
Classifier: Topic :: Scientific/Engineering :: Information Analysis
Classifier: Topic :: Text Processing :: Filters
Requires-Python: >=3.7
License-File: LICENSE
Requires-Dist: pandas (>=1.0.0)
